poly/__init__.py
libold_poly_porting-1.3.dist-info/METADATA
libold_poly_porting-1.3.dist-info/WHEEL
libold_poly_porting-1.3.dist-info/top_level.txt
libold_poly_porting-1.3.dist-info/RECORD
